odoo/addons/website_sale_product_attachment/README.rst
odoo/addons/website_sale_product_attachment/__init__.py
odoo/addons/website_sale_product_attachment/__manifest__.py
odoo/addons/website_sale_product_attachment/demo/assets.xml
odoo/addons/website_sale_product_attachment/i18n/ca.po
odoo/addons/website_sale_product_attachment/i18n/es.po
odoo/addons/website_sale_product_attachment/i18n/fr.po
odoo/addons/website_sale_product_attachment/i18n/it.po
odoo/addons/website_sale_product_attachment/i18n/nl.po
odoo/addons/website_sale_product_attachment/i18n/website_sale_product_attachment.pot
odoo/addons/website_sale_product_attachment/migrations/13.0.2.0.0/post-migration.py
odoo/addons/website_sale_product_attachment/migrations/13.0.2.0.0/pre-migration.py
odoo/addons/website_sale_product_attachment/models/__init__.py
odoo/addons/website_sale_product_attachment/models/ir_attachment.py
odoo/addons/website_sale_product_attachment/models/product_template.py
odoo/addons/website_sale_product_attachment/readme/CONFIGURE.rst
odoo/addons/website_sale_product_attachment/readme/CONTRIBUTORS.rst
odoo/addons/website_sale_product_attachment/readme/DESCRIPTION.rst
odoo/addons/website_sale_product_attachment/readme/ROADMAP.rst
odoo/addons/website_sale_product_attachment/readme/USAGE.rst
odoo/addons/website_sale_product_attachment/static/description/backend-attachment.png
odoo/addons/website_sale_product_attachment/static/description/backend-product.png
odoo/addons/website_sale_product_attachment/static/description/frontend-download.gif
odoo/addons/website_sale_product_attachment/static/description/frontend-icons.png
odoo/addons/website_sale_product_attachment/static/description/icon.png
odoo/addons/website_sale_product_attachment/static/description/index.html
odoo/addons/website_sale_product_attachment/static/src/js/website_tour.js
odoo/addons/website_sale_product_attachment/templates/product_template.xml
odoo/addons/website_sale_product_attachment/tests/__init__.py
odoo14_addon_website_sale_product_attachment-14.0.1.0.1.dev9.dist-info/METADATA
odoo14_addon_website_sale_product_attachment-14.0.1.0.1.dev9.dist-info/WHEEL
odoo14_addon_website_sale_product_attachment-14.0.1.0.1.dev9.dist-info/top_level.txt
odoo14_addon_website_sale_product_attachment-14.0.1.0.1.dev9.dist-info/RECORD
